<?xml version="1.0" encoding="UTF-8" standalone="no"?>
<bundle>
  <SocialIntegration>
    <messages>
      <createdBy>a été créé par</createdBy>
      <editedBy>a été édité par</editedBy>
      <system>le système</system>
      <readmore>...Lire la suite.</readmore>
      <editTitle>Le titre a été mis à jour: {0}</editTitle>
      <editSummary>Le sommaire a été mis à jour: {0}</editSummary>
      <editContent>Le contenu a été mis à jour.</editContent>
      <attachmentAdded>Des fichiers ont été attachés.</attachmentAdded>
      <attachmentRemoved>Des fichiers on été supprimés.</attachmentRemoved>
      <categoryAdded>La catégorie: {0} a été ajoutée.</categoryAdded>
      <categoryRemoved>La catégorie: {0} a été supprimée.</categoryRemoved>
      <tagAdded>Tag: {0} has been added.</tagAdded>
      <tagsAdded>Tags: {0} has been added.</tagsAdded>
      <tagRemoved>Tag: {0} has been removed.</tagRemoved>
      <tagsRemoved>Tags: {0} has been removed.</tagsRemoved>
      <stateChange>
        <pending>La publication est maintenant en attente.</pending>
        <approved>La publication a été approuvée.</approved>
        <staged>La publication est prête.</staged>
        <published>La publication est publiée.</published>
      </stateChange>
      <contentMoved>La publication a été déplacé: {0}</contentMoved>
      <revisionChanged>La publication a été restauré à la version: {0}</revisionChanged>
      <version>Version: {0}</version>
    </messages>
    <publicationStates>
      <archived>Archivé</archived>
      <obsolete>Obsolète</obsolete>
      <unpublished>Non Publié</unpublished>
      <draft>Brouillon</draft>
      <pending>En attente</pending>
      <approved>Approuvé</approved>
      <inreview>En revue</inreview>
      <staged>Prêt à publier</staged>
      <published>Publié</published>
      <live>Publié</live>
    </publicationStates>
  </SocialIntegration>
</bundle>
